AUTHORS
LICENSE
MANIFEST.in
README.rst
setup.py
django_predicate.egg-info/PKG-INFO
django_predicate.egg-info/SOURCES.txt
django_predicate.egg-info/dependency_links.txt
django_predicate.egg-info/top_level.txt
predicate/__init__.py
predicate/debug.py
predicate/lookup_utils.py
predicate/predicate.py