Metadata-Version: 2.1
Name: django-predicate
Version: 2.0.1
Summary: A predicate class constructed like Django Q objects, used to test whether a new or modified model would match a query
Home-page: http://github.com/django-predicate/django-predicate
Author: Preston Holmes
Author-email: preston@ptone.com
License: BSD
Classifier: Development Status :: 3 - Alpha
Classifier: Environment :: Web Environment
Classifier: Framework :: Django
Classifier: Intended Audience :: Developers
Classifier: License :: OSI Approved :: BSD License
Classifier: Operating System :: OS Independent
Classifier: Programming Language :: Python
Classifier: Programming Language :: Python :: 3.6
Classifier: Programming Language :: Python :: 3.7
Classifier: Programming Language :: Python :: 3.10
Classifier: Topic :: Utilities
License-File: LICENSE
License-File: AUTHORS
